[
  {
    "id": "1962-general",
    "title": "1962: The Last Winter In Moscow Mitwirkende gesucht",
    "project": "1962: The Last Winter In Moscow",
    "status": "Offen",
    "tags": [
      "Sound",
      "Modeling",
      "Roblox",
      "Nicht-kommerzielles Teamprojekt"
    ],
    "date": "2026-06-06",
    "url": "/de-de/find/1962general.html",
    "summary": "Gesucht werden Sound- und Modeling-Mitwirkende für die Atmosphäre von 1962: The Last Winter In Moscow."
  },
  {
    "id": "stelrun",
    "title": "StelLive Fan-Game Künstler gesucht",
    "project": "StelLive Fan-Game",
    "status": "Geschlossen",
    "tags": [
      "Art",
      "2D",
      "Fan-Game",
      "Geschlossen"
    ],
    "date": "2026-05-17",
    "url": "/de-de/find/stelrunartist.html",
    "summary": "Ausschreibung für 2D-Grafik, Illustration und UI-Künstler."
  }
]
